laplaciannb/__init__.py
laplaciannb/bayes.py
laplaciannb/fingerprint_utils.py
laplaciannb/legacy/LaplacianNB.py
laplaciannb-0.8.0.dist-info/METADATA
laplaciannb-0.8.0.dist-info/WHEEL
laplaciannb-0.8.0.dist-info/top_level.txt
laplaciannb-0.8.0.dist-info/RECORD
