Metadata-Version: 2.4
Name: laplaciannb
Version: 0.8.0
Summary: **LaplacianNB** is a Python module developed at **Novartis AG** for Naive Bayes classifier for laplacian modified models based on scikit-learn Naive Bayes implementation.
Author-email: Bartosz Baranowski <bartosz.baranowski@novartis.com>
License: BSD 3
Requires-Python: >=3.10
Requires-Dist: rdkit>=2024.3.5
Requires-Dist: scikit-learn>=1.7.0
Requires-Dist: pandas>=2.2.3
Requires-Dist: scipy>=1.6.0
Requires-Dist: tqdm>=4.67.1
